CHANGES.txt
CONTRIBUTORS.txt
README.txt
bootstrap.py
buildout.cfg
setup.cfg
setup.py
plone/__init__.py
plone.recipe.pound.egg-info/PKG-INFO
plone.recipe.pound.egg-info/SOURCES.txt
plone.recipe.pound.egg-info/dependency_links.txt
plone.recipe.pound.egg-info/entry_points.txt
plone.recipe.pound.egg-info/namespace_packages.txt
plone.recipe.pound.egg-info/not-zip-safe
plone.recipe.pound.egg-info/requires.txt
plone.recipe.pound.egg-info/top_level.txt
plone/recipe/__init__.py
plone/recipe/pound/README.txt
plone/recipe/pound/__init__.py
plone/recipe/pound/build.py
plone/recipe/pound/config.py
plone/recipe/pound/pound.cfg.tpl
plone/recipe/pound/pound_backend.cfg_tmpl
plone/recipe/pound/pound_balancer.cfg_tmpl
plone/recipe/pound/poundcontrol.tpl
plone/recipe/pound/poundctl.tpl
plone/recipe/pound/poundrun.tpl
plone/recipe/pound/utils.py
plone/recipe/pound/docs/building.txt
plone/recipe/pound/docs/configuring.txt
plone/recipe/pound/docs/technical.txt
plone/recipe/pound/tests/Pound-2.3.2.tgz
plone/recipe/pound/tests/__init__.py
plone/recipe/pound/tests/test_pounddocs.py