Metadata-Version: 1.0
Name: plone.recipe.pound
Version: 0.5.5
Summary: Recipe to install and configure Pound
Home-page: http://plone.org/products/plone-recipes
Author: Ingeniweb
Author-email: support@ingeniweb.com
License: GPL
Keywords: pound zope plone recipe
Platform: UNKNOWN
Classifier: Programming Language :: Python
Classifier: Topic :: Software Development :: Libraries :: Python Modules
